gdsfactoryhub/__init__.py
gdsfactoryhub/api_client.py
gdsfactoryhub/client.py
gdsfactoryhub/columns.py
gdsfactoryhub/errors.py
gdsfactoryhub/helpers.py
gdsfactoryhub/query_client.py
gdsfactoryhub/schemas.py
gdsfactoryhub/utils.py
gdsfactoryhub/functions/device_data/fsr.py
gdsfactoryhub/functions/device_data/linear_fit.py
gdsfactoryhub/functions/device_data/rolling_window.py
gdsfactoryhub/functions/die/aggregate_device_analyses.py
gdsfactoryhub/functions/die/cutback_loss.py
gdsfactoryhub/functions/die/iv_sheet_resistance.py
gdsfactoryhub/functions/die/propagation_loss.py
gdsfactoryhub/functions/wafer/aggregate_die_analyses.py
gdsfactoryhub-0.1.13.dist-info/METADATA
gdsfactoryhub-0.1.13.dist-info/WHEEL
gdsfactoryhub-0.1.13.dist-info/RECORD
