Metadata-Version: 2.4
Name: gdsfactoryhub
Version: 0.1.13
Summary: Software Development Kit - SDK for DoData
Author-email: DoPlayDo <contact@doplaydo.com>
Classifier: Operating System :: OS Independent
Classifier: Programming Language :: Python :: 3.11
Classifier: Programming Language :: Python :: 3.12
Requires-Python: >=3.11
Requires-Dist: dotenv>=0.9.9
Requires-Dist: httpx>=0.28.1
Requires-Dist: matplotlib>=3.10.5
Requires-Dist: orjson>=3.10.18
Requires-Dist: pandas>=2.2.3
Requires-Dist: pillow>=11.2.1
Requires-Dist: postgrest==2.19.0
Requires-Dist: pyarrow>=20.0.0
Requires-Dist: pydantic-settings
Requires-Dist: tenacity>=9.1.2
Requires-Dist: tqdm>=4.67.1
Provides-Extra: dev
Requires-Dist: build>=1.3.0; extra == 'dev'
Requires-Dist: ipykernel>=6.30.1; extra == 'dev'
Requires-Dist: mkdocs-material>=9.6.16; extra == 'dev'
Requires-Dist: mkdocs-minify-plugin>=0.8.0; extra == 'dev'
Requires-Dist: mkdocs>=1.6.1; extra == 'dev'
Requires-Dist: mkdocstrings-python>=1.16.12; extra == 'dev'
Requires-Dist: mkdocstrings>=0.30.0; extra == 'dev'
Requires-Dist: mkinit>=1.1.0; extra == 'dev'
Requires-Dist: nbconvert>=7.16.6; extra == 'dev'
Requires-Dist: papermill>=2.6.0; extra == 'dev'
Requires-Dist: pre-commit>=4.3.0; extra == 'dev'
Requires-Dist: pymdown-extensions>=10.16.1; extra == 'dev'
Requires-Dist: pyright>=1.1.403; extra == 'dev'
Requires-Dist: pytest>=8.4.1; extra == 'dev'
Requires-Dist: ruff>=0.12.8; extra == 'dev'
Requires-Dist: tbump>=6.11.0; extra == 'dev'
Requires-Dist: twine>=6.1.0; extra == 'dev'
Requires-Dist: uv>=0.8.10; extra == 'dev'
Requires-Dist: wheel>=0.45.1; extra == 'dev'
